{
  "@context" : "http://iiif.io/api/presentation/2/context.json",
  "@id" : "https://JodyButterworth.github.io/Djenne-display/manifests/manifest13.json",
  "@type" : "sc:Manifest",
  "label" : "[Click to edit label]",
  "metadata" : [ ],
  "description" : [ {
    "@value" : "[Click to edit description]",
    "@language" : "en"
  } ],
  "license" : "https://creativecommons.org/licenses/by/3.0/",
  "attribution" : "[Click to edit attribution]",
  "sequences" : [ {
    "@id" : "http://eba20b4c-2587-4d4d-be85-b0d3dd8d0bdd",
    "@type" : "sc:Sequence",
    "label" : [ {
      "@value" : "Normal Sequence",
      "@language" : "en"
    } ],
    "canvases" : [ {
      "@id" : "http://342b8d27-8cf9-45b7-ad5b-4508e449751e",
      "@type" : "sc:Canvas",
      "label" : "Empty canvas",
      "height" : 3024,
      "width" : 4032,
      "images" : [ {
        "@context" : "http://iiif.io/api/presentation/2/context.json",
        "@id" : "http://cf7be034-b7ce-4b2f-9c7d-4b119795da60",
        "@type" : "oa:Annotation",
        "motivation" : "sc:painting",
        "resource" : {
          "@id" : "https://jodybutterworth.github.io/Djenne-display/images/Image13/full/full/0/default.jpg",
          "@type" : "dctypes:Image",
          "format" : "image/jpeg",
          "service" : {
            "@context" : "http://iiif.io/api/image/2/context.json",
            "@id" : "https://jodybutterworth.github.io/Djenne-display/images/Image13",
            "profile" : "http://iiif.io/api/image/2/level0.json"
          },
          "height" : 3024,
          "width" : 4032
        },
        "on" : "http://342b8d27-8cf9-45b7-ad5b-4508e449751e"
      } ],
      "related" : ""
    } ]
  } ],
  "structures" : [ ]
}